flake8_escaping_style.py
flake8_escaping_style-0.1.2.dist-info/LICENSE
flake8_escaping_style-0.1.2.dist-info/METADATA
flake8_escaping_style-0.1.2.dist-info/WHEEL
flake8_escaping_style-0.1.2.dist-info/entry_points.txt
flake8_escaping_style-0.1.2.dist-info/top_level.txt
flake8_escaping_style-0.1.2.dist-info/RECORD
