Metadata-Version: 2.1
Name: flake8-escaping-style
Version: 0.1.2
Summary: A flake8 plugin to use consistent escaping style in string or bytes literals
Home-page: https://github.com/bmispelon/flake8-escaping-style
Author: Baptiste Mispelon
Author-email: bmispelon@gmail.com
License: MIT
Project-URL: Bug Tracker, https://github.com/bmispelon/flake8-escaping-style/issues
Platform: UNKNOWN
Classifier: Framework :: Flake8
Classifier: Environment :: Console
Classifier: Intended Audience :: Developers
Classifier: License :: OSI Approved :: MIT License
Classifier: Programming Language :: Python
Classifier: Programming Language :: Python :: 3
Classifier: Programming Language :: Python :: 3.7
Classifier: Programming Language :: Python :: 3.8
Classifier: Programming Language :: Python :: 3.9
Classifier: Topic :: Software Development :: Libraries :: Python Modules
Classifier: Topic :: Software Development :: Quality Assurance
Requires-Python: >=3.7
License-File: LICENSE
Requires-Dist: flake8 (>3.0.0)
